localsssend/__init__.py
localsssend-0.0.0.dist-info/METADATA
localsssend-0.0.0.dist-info/WHEEL
localsssend-0.0.0.dist-info/licenses/LICENSE
localsssend-0.0.0.dist-info/RECORD
