Metadata-Version: 2.4
Name: localsssend
Version: 0.0.0
Summary: A Python implementation of the Localsend protocol.
Author-email: Christoph Schlosser <code@c.onl>
License-Expression: BSD-3-Clause
License-File: LICENSE
Classifier: Operating System :: OS Independent
Classifier: Programming Language :: Python :: 3
Requires-Python: >=3.9
